[
  { "id": 1,  "title": "천재의 공통점, 습관",            "category": "습관", "summary": "타고난 천재도 결국 매일 반복한 습관이 만든 결과입니다. 재능보다 루틴이 오래 갑니다.",                          "mission": "아이와 함께 매일 5분 같은 시간에 할 작은 루틴 1개 정하기." },
  { "id": 2,  "title": "다양한 나라의 교육법",            "category": "공부", "summary": "핀란드의 자율, 일본의 절제, 미국의 토론 — 정답은 하나가 아닙니다. 우리 아이에 맞는 조합을 찾는 게 핵심입니다.",     "mission": "오늘 본 다른 나라 교육법 1가지 아이에게 이야기해 주기." },
  { "id": 3,  "title": "오타니 쇼헤이 루틴",              "category": "습관", "summary": "세계 최고의 선수도 9칸 만다라트로 목표를 쪼갰습니다. 거창한 계획보다 칸을 채우는 힘이 큽니다.",                  "mission": "A4 한 장에 아이의 목표 9칸을 함께 그려 보기." },
  { "id": 4,  "title": "스스로 불을 켠 사람",             "category": "공부", "summary": "스탠퍼드 이진영 교수의 비결은 ‘스스로 질문하는 공부’였습니다. 답보다 질문이 먼저입니다.",                      "mission": "아이가 오늘 배운 것에 ‘왜?’ 질문 3개 만들어 보게 하기." },
  { "id": 5,  "title": "장애를 극복한 박사님의 비결",     "category": "인성", "summary": "한계는 환경이 아니라 태도에서 결정됩니다. 포기하지 않는 마음이 가장 큰 재능입니다.",                          "mission": "아이가 ‘못한다’고 한 일 1가지를 함께 한 걸음만 시도해 보기." },
  { "id": 6,  "title": "하버드 수석 졸업생의 태도",       "category": "공부", "summary": "수석들의 공통점은 ‘긴 시간 앉아 있기’가 아니라 ‘몰입과 회복의 리듬’이었습니다.",                              "mission": "오늘 25분 집중 + 5분 휴식(포모도로) 한 사이클 같이 해 보기." },
  { "id": 7,  "title": "매너, 인생을 지키는 무기",        "category": "인성", "summary": "예의는 아이가 어디를 가든 환영받게 만드는 평생의 자산입니다.",                                                "mission": "오늘 ‘안녕하세요·감사합니다·죄송합니다’ 3마디 함께 연습." },
  { "id": 8,  "title": "자존감을 올리는 방법",            "category": "인성", "summary": "자존감은 칭찬보다 ‘있는 그대로 인정받는 경험’에서 자랍니다.",                                                "mission": "아이의 오늘 모습 그대로 1문장 인정해 주기." },
  { "id": 9,  "title": "도전 정신 키우기",                "category": "인성", "summary": "실패해도 괜찮다는 안전감이 있어야 아이는 새로운 것을 시도합니다.",                                            "mission": "오늘 아이가 처음 해 보는 일 1가지 만들어 주기." },
  { "id": 10, "title": "책과 친해지는 첫 10분",           "category": "습관", "summary": "독서는 양보다 ‘매일 같은 시간 10분’의 리듬에서 시작됩니다.",                                                  "mission": "잠들기 전 10분, 같은 자리에서 책 읽기." },
  { "id": 11, "title": "IQ를 넘는 부모의 반응",           "category": "관계", "summary": "아이의 말에 부모가 어떻게 반응하느냐가 지능보다 큰 영향을 줍니다.",                                          "mission": "아이의 말 끝에 ‘오, 더 얘기해 줘’ 3번 사용하기." },
  { "id": 12, "title": "좋은 관계를 위한 대화법",         "category": "관계", "summary": "‘왜 그랬어’ 대신 ‘무슨 일이 있었어’가 마음을 엽니다.",                                                      "mission": "오늘 아이에게 ‘왜’ 대신 ‘무슨 일’로 물어보기." },
  { "id": 13, "title": "말 없는 아이의 자기표현",         "category": "관계", "summary": "말이 적은 아이는 그림·글·놀이로 마음을 표현합니다. 통로를 다양하게 열어 주세요.",                          "mission": "오늘 아이와 그림 한 장으로 ‘오늘의 기분’ 표현해 보기." },
  { "id": 14, "title": "능동적인 아이로 키우기",          "category": "습관", "summary": "선택권이 있을 때 아이는 비로소 책임을 배웁니다.",                                                            "mission": "오늘 옷·간식·놀이 중 1가지를 아이가 직접 고르게 하기." },
  { "id": 15, "title": "산만한 아이 공부시키는 법",       "category": "습관", "summary": "산만함은 의지가 아니라 환경의 문제일 수 있습니다. 책상 위를 비우는 것부터.",                                "mission": "공부 시작 전 책상 위 물건 3개 치우기 규칙 정하기." },
  { "id": 16, "title": "유대인 교육 따라 하기",           "category": "공부", "summary": "유대인 교육의 핵심은 정답이 아니라 ‘질문하는 힘’입니다.",                                                    "mission": "저녁 식사 때 아이에게 답 없는 질문 1개 던지기." },
  { "id": 17, "title": "부모와 아이가 함께 실천",         "category": "관계", "summary": "부모가 하지 않는 것을 아이에게 시키면 따르지 않습니다.",                                                    "mission": "아이에게 시키고 싶은 행동을 부모가 먼저 1번 보여 주기." },
  { "id": 18, "title": "AI 시대 아이 교육 방향",          "category": "공부", "summary": "정답을 외우는 시대는 끝났습니다. 질문하고 활용하는 능력이 핵심입니다.",                                      "mission": "아이와 함께 AI에게 궁금한 것 1가지 물어보기." },
  { "id": 19, "title": "하워드 가드너의 다중지능",        "category": "공부", "summary": "지능은 8가지 — 언어·논리·공간·음악·신체·대인·자기성찰·자연. 우리 아이의 강점을 찾아 주세요.",          "mission": "아이가 가장 빛나는 순간 1가지 메모해 두기." },
  { "id": 20, "title": "UN으로 보내는 교육",              "category": "공부", "summary": "글로벌 인재의 출발점은 영어가 아니라 ‘세상을 향한 호기심’입니다.",                                          "mission": "지구본·세계지도에서 오늘의 나라 1곳 함께 찾아보기." },
  { "id": 21, "title": "독서가 아이에게 미치는 영향",     "category": "공부", "summary": "독서는 어휘·사고·공감 능력을 동시에 키우는 거의 유일한 활동입니다.",                                        "mission": "오늘 아이에게 책 1쪽 소리 내어 읽어 주기." },
  { "id": 22, "title": "감정이 풀려야 집중이 열린다",     "category": "인성", "summary": "마음에 응어리가 있는 아이는 절대 집중할 수 없습니다.",                                                      "mission": "공부 전 ‘오늘 기분 어때?’ 한 번 물어보기." },
  { "id": 23, "title": "동기 없는 아이의 공부",           "category": "공부", "summary": "동기는 강요로 만들 수 없습니다. ‘작은 성공’의 경험이 동기를 만듭니다.",                                    "mission": "오늘 아이가 ‘다 했다!’ 외칠 만한 작은 과제 1개 주기." },
  { "id": 24, "title": "남들과 다른 생각을 하라",         "category": "인성", "summary": "정답 사회에서 가장 귀한 능력은 ‘다른 답을 두려워하지 않는 용기’입니다.",                                    "mission": "아이의 엉뚱한 답에 ‘오 신선한데?’로 반응하기." },
  { "id": 25, "title": "예술이 자존감을 바꾸는 순간",     "category": "인성", "summary": "예술은 잘하고 못하고가 없습니다. ‘내 것’을 만든 경험이 자존감을 만듭니다.",                                "mission": "오늘 아이의 그림·작품을 잘 보이는 곳에 붙여 두기." },
  { "id": 26, "title": "말보다 강한 부모의 눈빛",         "category": "관계", "summary": "아이는 부모의 말이 아니라 눈빛을 먼저 읽습니다.",                                                            "mission": "오늘 아이의 눈을 3초 이상 바라보며 미소 짓기." },
  { "id": 27, "title": "평생에 남는 부모의 한마디",       "category": "관계", "summary": "스쳐 지나가는 한마디가 아이의 평생 자아상을 만듭니다.",                                                      "mission": "오늘 아이에게 ‘너는 ~한 사람이야’ 긍정 문장 1개 말해 주기." },
  { "id": 28, "title": "악기 하나가 평생 친구",           "category": "습관", "summary": "악기는 외로움 속에서도 아이를 지켜 주는 평생의 동반자입니다.",                                              "mission": "아이와 함께 좋아하는 음악 1곡 끝까지 들어보기." },
  { "id": 29, "title": "음악은 평생의 친구",              "category": "습관", "summary": "음악은 감정의 언어입니다. 매일 들려주는 멜로디가 정서를 만듭니다.",                                          "mission": "아침에 일어나서 좋아하는 음악 1곡 틀어 주기." },
  { "id": 30, "title": "음악과 공부로 날개를 단 소녀",    "category": "공부", "summary": "예술과 공부는 적이 아닙니다. 서로 다른 뇌를 깨워 시너지를 만듭니다.",                                        "mission": "공부 시작 전 좋아하는 음악 1곡 듣는 의식 만들기." },
  { "id": 31, "title": "정직하게 산다는 것",              "category": "인성", "summary": "정직은 손해 보는 일이 아니라 신뢰라는 가장 큰 자산을 쌓는 일입니다.",                                        "mission": "오늘 부모가 작은 거짓말도 하지 않기 챌린지." },
  { "id": 32, "title": "듣는 대로 성장한다",              "category": "관계", "summary": "아이는 자기에 대해 들은 말을 그대로 자기 정체성으로 만듭니다.",                                              "mission": "‘게으르다·느리다·못한다’ 단어 오늘 하루 0회." },
  { "id": 33, "title": "성적보다 먼저 가르칠 세 가지",    "category": "인성", "summary": "정직, 책임, 감사 — 이 세 가지는 성적보다 먼저 가르쳐야 할 기본기입니다.",                                  "mission": "오늘 셋 중 1가지를 식탁에서 함께 이야기하기." },
  { "id": 34, "title": "결과가 아닌 과정을 칭찬하라",     "category": "관계", "summary": "‘잘했다’보다 ‘끝까지 했네’가 아이를 더 강하게 만듭니다.",                                                    "mission": "오늘 칭찬할 때 ‘과정 동사’ 한 번 사용하기." },
  { "id": 35, "title": "실패를 두려워하지 않는 아이",     "category": "인성", "summary": "실패해도 사랑받는다는 확신이 도전을 만듭니다.",                                                              "mission": "아이의 오늘 실수에 ‘괜찮아, 다시 해 보자’ 1번 말하기." },
  { "id": 36, "title": "탁월함은 태도에서 온다",          "category": "습관", "summary": "탁월함은 재능이 아니라 ‘대충 하지 않는 태도’의 누적입니다.",                                                "mission": "오늘 한 가지 일을 ‘평소보다 1단계 더 정성껏’ 해 보기." },
  { "id": 37, "title": "부모의 작은 목표가 큰 미래로",    "category": "관계", "summary": "부모가 자기 삶에 목표가 있을 때 아이도 목표를 갖게 됩니다.",                                                "mission": "오늘의 ‘부모 자신의 목표’ 1가지 적어 보기." },
  { "id": 38, "title": "성격은 부모의 생각에서 시작",     "category": "관계", "summary": "‘우리 아이는 ~해’라는 부모의 정의가 아이의 성격을 만듭니다.",                                                "mission": "아이에 대한 부정적 라벨 1개를 긍정으로 바꿔 보기." },
  { "id": 39, "title": "내면의 확신이 잠재력을 깨운다",   "category": "관계", "summary": "부모의 흔들림 없는 믿음이 아이의 가장 단단한 토대가 됩니다.",                                                "mission": "‘나는 우리 아이를 믿는다’ 거울 보고 1번 말하기." },
  { "id": 40, "title": "부모가 먼저 성장하라",            "category": "관계", "summary": "아이는 가르침이 아니라 부모의 성장 모습을 보고 자랍니다.",                                                  "mission": "오늘 부모가 새로 배운 것 1가지 아이에게 말해 주기." },
  { "id": 41, "title": "인내가 명품을 만든다",            "category": "인성", "summary": "기다림은 가장 어렵고 가장 강력한 교육입니다.",                                                              "mission": "아이가 스스로 할 일 1가지, 끝까지 기다려 주기." },
  { "id": 42, "title": "나눔과 배려로 가치관 형성",       "category": "인성", "summary": "받는 기쁨보다 주는 기쁨을 아는 아이가 더 단단하게 자랍니다.",                                                "mission": "오늘 아이와 함께 누군가에게 작은 친절 1번 베풀기." },
  { "id": 43, "title": "감사를 아는 아이는 다르다",       "category": "인성", "summary": "감사는 행복의 가장 단순하고 강력한 습관입니다.",                                                              "mission": "잠들기 전 ‘오늘 감사한 일 1가지’ 함께 말하기." },
  { "id": 44, "title": "정성과 열정의 ‘성공 DNA’",        "category": "습관", "summary": "성공의 유전자는 타고나는 것이 아니라 매일의 정성에서 만들어집니다.",                                          "mission": "오늘 한 가지 일에 ‘대충 안 하기’ 약속 지키기." },
  { "id": 45, "title": "인생 멘토는 바로 부모",           "category": "관계", "summary": "아이의 첫 멘토이자 가장 오래 남는 멘토는 부모입니다.",                                                        "mission": "오늘 아이에게 부모의 어릴 적 이야기 1개 들려주기." },
  { "id": 46, "title": "자녀를 살리는 언어의 힘",         "category": "관계", "summary": "말은 칼이 될 수도, 약이 될 수도 있습니다. 부모의 언어가 아이를 살립니다.",                                  "mission": "오늘 아이에게 한 부정어를 긍정어로 바꿔 말하기." },
  { "id": 47, "title": "방송에 나온 자녀 공부법",         "category": "공부", "summary": "화제가 된 공부법의 공통점은 결국 ‘꾸준함’과 ‘부모의 일관성’이었습니다.",                                  "mission": "이번 주에 지킬 작은 학습 규칙 1개 정하기." },
  { "id": 48, "title": "두 부모의 다른 교육관",           "category": "관계", "summary": "교육관이 다를 때 가장 혼란스러운 건 아이입니다. 일치보다 ‘조율’이 필요합니다.",                              "mission": "오늘 배우자와 교육 원칙 1가지 합의해 보기." },
  { "id": 49, "title": "어머니의 사랑이 보여 준 것",      "category": "관계", "summary": "조건 없는 사랑은 어떤 교육법보다 강력합니다.",                                                              "mission": "아이에게 ‘있는 그대로 사랑해’ 1번 말해 주기." },
  { "id": 50, "title": "MBTI로 내 아이 이해하기",         "category": "관계", "summary": "기질을 알면 잔소리가 줄고, 이해가 늘어납니다.",                                                              "mission": "내 아이의 성향 키워드 3개 적어 보기." },
  { "id": 51, "title": "여행을 통한 자녀 교육",           "category": "공부", "summary": "여행은 책 100권보다 큰 교실입니다.",                                                                          "mission": "이번 주말, 가까운 새로운 장소 1곳 함께 가 보기." },
  { "id": 52, "title": "괴테 어머니의 지혜",              "category": "관계", "summary": "괴테를 만든 건 천재성이 아니라 매일 밤 이야기를 들려준 어머니였습니다.",                                    "mission": "오늘 잠들기 전 짧은 이야기 1편 들려주기." },
  { "id": 53, "title": "책으로 만난 위대한 교육자",       "category": "공부", "summary": "고전 교육서 한 권은 부모의 시선을 바꿉니다.",                                                                "mission": "교육서 1권에서 마음에 든 문장 1줄 옮겨 적기." },
  { "id": 54, "title": "옳고 그름보다 보여 줄 것",        "category": "인성", "summary": "아이는 부모의 말이 아니라 ‘부모의 등’을 보고 배웁니다.",                                                    "mission": "오늘 아이에게 보여 주고 싶은 행동을 먼저 하기." },
  { "id": 55, "title": "부모의 약속이 인생의 기준",       "category": "관계", "summary": "약속을 지키는 부모는 아이에게 ‘세상은 믿을 만한 곳’이라는 감각을 줍니다.",                                  "mission": "오늘 아이와 한 약속 1개를 메모하고 반드시 지키기." },
  { "id": 56, "title": "우주적 목적은 신의 선물",         "category": "인성", "summary": "모든 아이는 자기만의 사명을 갖고 태어납니다. 부모는 그 길을 막지 않으면 됩니다.",                            "mission": "오늘 아이가 좋아하는 것 1가지를 가만히 관찰하기." },
  { "id": 57, "title": "무에서 유를 창조하는 가족",       "category": "관계", "summary": "환경이 부족해도 가족 안의 ‘함께 만드는 경험’이 모든 것을 만들어 냅니다.",                                  "mission": "오늘 가족이 함께 ‘없는 것에서 만든 놀이’ 1가지 해 보기." },
  { "id": 58, "title": "D-day보다 V-day",                  "category": "습관", "summary": "마감보다 ‘승리의 날(Victory)’을 그리는 아이가 더 멀리 갑니다.",                                              "mission": "아이가 이루고 싶은 V-day 1개 함께 그려 보기." },
  { "id": 59, "title": "영어의 필요성을 느낀 순간",       "category": "공부", "summary": "필요는 가장 강력한 동기입니다. 영어가 ‘쓸 일’이 있을 때 아이는 움직입니다.",                                "mission": "오늘 영어가 쓰이는 장면 1가지 함께 찾아보기." },
  { "id": 60, "title": "영어의 ‘끌림’은 어디서 올까",     "category": "공부", "summary": "흥미는 가르치는 것이 아니라 ‘좋아하는 콘텐츠’에서 자연스럽게 옵니다.",                                      "mission": "아이가 좋아하는 주제의 영어 영상 5분 함께 보기." },
  { "id": 61, "title": "유대인식 언어 습득",              "category": "공부", "summary": "유대인은 외우기 전에 ‘소리 내어 읽고 토론’합니다. 언어는 입에서 시작됩니다.",                                "mission": "오늘 책 한 문단을 아이와 소리 내어 함께 읽기." },
  { "id": 62, "title": "성적 너머, 진짜 영어의 힘",       "category": "공부", "summary": "영어의 진짜 힘은 점수가 아니라 ‘세상과 연결되는 능력’입니다.",                                                "mission": "외국 친구·콘텐츠와 만나는 작은 경험 1가지 만들어 주기." },
  { "id": 63, "title": "유대인 교육을 따라서",            "category": "공부", "summary": "유대인 교육의 본질은 ‘질문, 토론, 가족 식탁’ 세 가지로 요약됩니다.",                                          "mission": "오늘 저녁 식탁에서 한 가지 주제로 5분 토론하기." },
  { "id": 64, "title": "유대인 교육 ‘토라’를 알다",       "category": "공부", "summary": "토라 교육은 ‘외우기 위한’ 것이 아니라 ‘질문하기 위한’ 텍스트였습니다.",                                      "mission": "아이가 읽은 글에 ‘질문 1개’ 만들어 보게 하기." },
  { "id": 65, "title": "외우기 달인, 유대인",             "category": "공부", "summary": "유대인의 암기력은 반복과 ‘의미 부여’에서 나옵니다. 외움도 이해 위에서 작동합니다.",                          "mission": "오늘 외운 것을 ‘왜 그런지’ 한 문장으로 설명하게 하기." },
  { "id": 66, "title": "내 아이, 유대인처럼 키우기",      "category": "공부", "summary": "거창한 교재가 아니라 ‘하브루타(짝 토론)’ 한 번이면 시작할 수 있습니다.",                                    "mission": "오늘 책 1쪽 읽고 아이와 1:1로 묻고 답하기." },
  { "id": 67, "title": "마음을 여는 또 하나의 언어, 악기", "category": "습관", "summary": "악기는 말로 표현하지 못하는 감정을 꺼내는 또 하나의 언어입니다.",                                              "mission": "오늘 아이와 손뼉·작은 타악기로 박자 맞추기." },
  { "id": 68, "title": "거실에서 시작되는 작은 기적",     "category": "관계", "summary": "교육의 출발점은 학원이 아니라 가족이 모이는 거실입니다.",                                                    "mission": "오늘 거실에 30분 ‘TV·폰 없는 시간’ 만들기." },
  { "id": 69, "title": "인생 계획, 교육 계획의 시작",     "category": "공부", "summary": "아이의 교육은 결국 ‘어떤 인생을 살게 하고 싶은가’에서 출발해야 합니다.",                                    "mission": "‘우리 아이가 어떤 어른이 되길 바라는가’ 1줄 적기." },
  { "id": 70, "title": "아빠가 교육의 중심이 되어야",     "category": "관계", "summary": "아빠의 참여는 아이의 자존감·사회성·학업 모두에 가장 큰 영향을 줍니다.",                                      "mission": "아빠가 오늘 아이와 단둘이 15분 보내기." }
]
